flowsim/flowsim.py
flowsim-0.0.0.dist-info/LICENSE
flowsim-0.0.0.dist-info/METADATA
flowsim-0.0.0.dist-info/WHEEL
flowsim-0.0.0.dist-info/top_level.txt
flowsim-0.0.0.dist-info/RECORD
