Metadata-Version: 2.1
Name: flowsim
Version: 0.0.0
Summary: A sript to simulate field-scale evapotranspiration and drainage
Author-email: Steen Christensen <sc@geo.au.dk>
License: MIT License
Classifier: Programming Language :: Python :: 3
Classifier: License :: OSI Approved :: MIT License
Classifier: Operating System :: OS Independent
Requires-Python: >=3.7
License-File: LICENSE
Requires-Dist: requests
Requires-Dist: importlib-metadata ; python_version < "3.8"
